tuilib.py
tuilib-4.1.0.0.dist-info/METADATA
tuilib-4.1.0.0.dist-info/WHEEL
tuilib-4.1.0.0.dist-info/top_level.txt
tuilib-4.1.0.0.dist-info/RECORD
