Metadata-Version: 2.4
Name: tuilib
Version: 4.1.0.0
Summary: A Python library for creating Terminal User Interfaces using curses
Home-page: https://github.com/replit-user/tuilib
Author: 
Author-email: umyashinderu@gmail.com
Classifier: Programming Language :: Python :: 3
Classifier: License :: OSI Approved :: MIT License
Classifier: Operating System :: OS Independent
Dynamic: author-email
Dynamic: classifier
Dynamic: description
Dynamic: description-content-type
Dynamic: home-page
Dynamic: summary
